fastapi_users_db_deta/__init__.py
fastapi_users_db_deta-0.2.3.dist-info/AUTHORS.rst
fastapi_users_db_deta-0.2.3.dist-info/LICENSE
fastapi_users_db_deta-0.2.3.dist-info/METADATA
fastapi_users_db_deta-0.2.3.dist-info/WHEEL
fastapi_users_db_deta-0.2.3.dist-info/entry_points.txt
fastapi_users_db_deta-0.2.3.dist-info/top_level.txt
fastapi_users_db_deta-0.2.3.dist-info/RECORD
