Metadata-Version: 2.1
Name: fastapi-users-db-deta
Version: 0.2.3
Summary: Sub-package for Deta Base support in FastAPI Users.
Home-page: https://github.com/ak4zh/fastapi_users_db_deta
Author: Akash Agarwal
Author-email: agwl.akash@gmail.com
License: MIT license
Keywords: fastapi_users_db_deta
Platform: UNKNOWN
Classifier: Development Status :: 2 - Pre-Alpha
Classifier: Intended Audience :: Developers
Classifier: License :: OSI Approved :: MIT License
Classifier: Natural Language :: English
Classifier: Programming Language :: Python :: 3
Classifier: Programming Language :: Python :: 3.6
Classifier: Programming Language :: Python :: 3.7
Classifier: Programming Language :: Python :: 3.8
Requires-Python: >=3.6
License-File: LICENSE
License-File: AUTHORS.rst
Requires-Dist: Click (>=7.0)
